Workbook

Sheet Overview
A1: CollectRx — Pilot Financial Model
A3: Pricing structure: Hybrid (monthly base + success fee on recovered AR). Insurer pays practice directly; CollectRx invoices the practice.
A5: Payment Flow — How Money Moves
B6: 1. Insurer → Practice | C6: Insurer adjudicates claim and sends EFT/cheque directly to the practice's bank account. | G6: CollectRx never touches this money. No money-transmitter risk.
B7: 2. Patient → Practice | C7: Patient pays residual balance (copay/deductible) directly to the practice via existing methods. | G7: Future phase: Patient-pay module routes via Stripe Connect — not in pilot.
B8: 3. CollectRx → Practice (invoice) | C8: At month-end, CollectRx generates an invoice: monthly base fee + success fee × recovered AR that month. | G8: Delivered via Stripe Billing. Auto-debit recommended (Net 0 / ACH pre-authorized).
B9: 4. Practice → CollectRx (payment) | C9: Practice's bank auto-debits invoice amount + HST. Funds settle in CollectRx operating account. | G9: Gross margin after Stripe fees (~2.9%) and variable costs (Vapi, Twilio) flows to the business.
A11: Color Legend
B12: Blue | C12: Hardcoded input (edit these)
B13: Black | C13: Formula / calculation
B14: Green | C14: Cross-sheet link
B15: Yellow fill | C15: Key assumption — review before using
A17: Sheets in this model
B18: Assumptions | C18: All input variables. Edit blue cells to change the model.
B19: Unit Economics | C19: Per-practice monthly P&L in steady state and at ramp stages.
B20: Pilot Projection | C20: 12-month view of 4 practices with staggered onboarding.
B21: Pricing Scenarios | C21: Sensitivity table: base fee × success fee % → revenue/practice.
B22: Sample Invoice | C22: What a monthly invoice to Dr. Hasan's practice looks like.
B25: Note: This is a planning model, not accounting or tax advice. Confirm HST handling and pricing structure with your CPA. CAD throughout.

Sheet Assumptions
A1: Assumptions — Edit Blue Cells
A2: All values CAD. Update inputs and the entire model recalculates.
A4: Pricing (Your Revenue Per Practice)
B5: Monthly base fee (CAD) | C5: 299 | D5: Keeps lights on during slow months; covers infra baseline.
B6: Success fee on recovered AR | C6: 0.12 | D6: Industry range 10-25%. 12% is competitive for AI-assisted RCM.
B7: HST rate (Ontario, pass-through) | C7: 0.13 | D7: Charged on invoice; remitted to CRA quarterly.
A9: Practice Operations (Per Practice, Steady State)
B10: Average monthly aged AR (>30 days) targeted by CollectRx | C10: 8000 | D10: Based on typical Canadian GP practice ($800K-$1.5M revenue, 8-12% AR aging).
B11: Recovery rate with CollectRx automation | C11: 0.7 | D11: vs. ~40-50% baseline without systematic follow-up.
B12: Ramp-up multiplier — Month 1 | C12: 0.3 | D12: First month: onboarding, schema discovery, calibration.
B13: Ramp-up multiplier — Month 2 | C13: 0.65 | D13: Vapi squad live, still learning practice-specific patterns.
B14: Ramp-up multiplier — Month 3+ | C14: 1 | D14: Full steady state.
A16: Variable Costs (Per Practice, Monthly)
B17: Vapi (AI voice agent) | C17: 280 | D17: ~2 hours active call time/day × Vapi per-minute rate.
B18: Twilio (telephony) | C18: 75 | D18: Per-minute + trunking, Canadian DIDs.
B19: Stripe fees on collected revenue | C19: 0.029 | D19: 2.9% on invoice total. Apply to revenue in formulas.
B20: Other per-practice variable (PIIVault, misc) | C20: 50 | D20: Tokenization API calls, incidental overhead.
A22: Fixed Costs (Company-wide, Monthly)
B23: Infrastructure baseline (Railway, DB, cache) | C23: 200 | D23: Non-variable portion.
B24: Legal / compliance amortized (PHIPA, PIPEDA) | C24: 300 | D24: Annualized advisory retainer ÷ 12.
B25: Insurance (E&O, cyber liability) | C25: 250 | D25: Essential once handling PHI-adjacent workflows.
B26: Software & tools (GitHub, Stripe, monitoring) | C26: 200 | D26: Aggregated SaaS stack.
B27: Founder draw / salary | C27: 0 | D27: Set to 0 for bootstrapped pilot; bump when cash-positive.
B29: Total monthly fixed costs | C29: =SUM(Assumptions!$C$23:$C$27) -> 950
A31: Pilot Onboarding Schedule
B32: Practice 1 — Dr. Hasan (Tenth Line) | C32: 1 | D32: Month the practice goes live (1-12).
B33: Practice 2 | C33: 3 | D33: Month the practice goes live (1-12).
B34: Practice 3 | C34: 5 | D34: Month the practice goes live (1-12).
B35: Practice 4 | C35: 7 | D35: Month the practice goes live (1-12).

Sheet Unit Economics
A1: Per-Practice Unit Economics
A2: One practice, monthly P&L at each ramp stage + annualized steady state.
B4: Line Item | C4: Month 1 (Ramp) | D4: Month 2 (Ramp) | E4: Month 3+ (Steady) | F4: Annualized (Steady)
B5: Ramp multiplier | C5: =Assumptions!$C$12 -> 0.3 | D5: =Assumptions!$C$13 -> 0.65 | E5: =Assumptions!$C$14 -> 1
A7: Revenue
B8: Monthly base fee | C8: =Assumptions!$C$5 -> 299 | D8: =Assumptions!$C$5 -> 299 | E8: =Assumptions!$C$5 -> 299 | F8: =E8*12 -> 3588
B9: Recovered AR attributed to CollectRx | C9: =Assumptions!$C$10*Assumptions!$C$11*C5 -> 1680 | D9: =Assumptions!$C$10*Assumptions!$C$11*D5 -> 3640 | E9: =Assumptions!$C$10*Assumptions!$C$11*E5 -> 5600 | F9: =E9*12 -> 67200
B10: Success fee revenue (% × recovered AR) | C10: =C9*Assumptions!$C$6 -> 201.6 | D10: =D9*Assumptions!$C$6 -> 436.8 | E10: =E9*Assumptions!$C$6 -> 672 | F10: =E10*12 -> 8064
B11: Total monthly revenue | C11: =C8+C10 -> 500.6 | D11: =D8+D10 -> 735.8 | E11: =E8+E10 -> 971 | F11: =F8+F10 -> 11652
A13: Variable Costs (per Practice)
B14: Vapi (voice AI) | C14: =Assumptions!$C$17 -> 280 | D14: =Assumptions!$C$17 -> 280 | E14: =Assumptions!$C$17 -> 280 | F14: =E14*12 -> 3360
B15: Twilio (telephony) | C15: =Assumptions!$C$18 -> 75 | D15: =Assumptions!$C$18 -> 75 | E15: =Assumptions!$C$18 -> 75 | F15: =E15*12 -> 900
B16: Other per-practice variable | C16: =Assumptions!$C$20 -> 50 | D16: =Assumptions!$C$20 -> 50 | E16: =Assumptions!$C$20 -> 50 | F16: =E16*12 -> 600
B17: Stripe processing fees | C17: =C11*Assumptions!$C$19 -> 14.5174 | D17: =D11*Assumptions!$C$19 -> 21.3382 | E17: =E11*Assumptions!$C$19 -> 28.159 | F17: =E17*12 -> 337.908
B18: Total variable costs | C18: =SUM(C14:C17) -> 419.5174 | D18: =SUM(D14:D17) -> 426.3382 | E18: =SUM(E14:E17) -> 433.159 | F18: =SUM(F14:F17) -> 5197.908
B20: Gross profit per practice | C20: =C11-C18 -> 81.0826 | D20: =D11-D18 -> 309.4618 | E20: =E11-E18 -> 537.841 | F20: =F11-F18 -> 6454.092
B21: Gross margin % | C21: =IFERROR(C20/C11,0) -> 0.16197083 | D21: =IFERROR(D20/D11,0) -> 0.42057869 | E21: =IFERROR(E20/E11,0) -> 0.55390422 | F21: =IFERROR(F20/F11,0) -> 0.55390422
A23: Implications
B24: Contribution per practice (steady state, monthly) | C24: =E20 -> 537.841
B25: Break-even practice count | C25: =CEILING(Assumptions!$C$29/E20,1) -> 2
B26: 12-month LTV per practice (steady state, no churn) | C26: =F20 -> 6454.092
B27: Assumed gross margin at steady state | C27: =E21 -> 0.55390422

Sheet Pilot Projection
A1: 12-Month Pilot Projection — 4 Practices (Staggered)
A2: Practices onboard per schedule in Assumptions. Each practice follows 3-month ramp curve.
B4: Line Item | C4: M1 | D4: M2 | E4: M3 | F4: M4 | G4: M5 | H4: M6 | I4: M7 | J4: M8 | K4: M9 | L4: M10 | M4: M11 | N4: M12 | O4: Year 1 Total
B5: Month # | C5: 1 | D5: 2 | E5: 3 | F5: 4 | G5: 5 | H5: 6 | I5: 7 | J5: 8 | K5: 9 | L5: 10 | M5: 11 | N5: 12
A7: Active Practices by Month
B8: Practice 1 (Dr. Hasan) | C8: =IF(C5>=Assumptions!$C$32,1,0) -> 1 | D8: =IF(D5>=Assumptions!$C$32,1,0) -> 1 | E8: =IF(E5>=Assumptions!$C$32,1,0) -> 1 | F8: =IF(F5>=Assumptions!$C$32,1,0) -> 1 | G8: =IF(G5>=Assumptions!$C$32,1,0) -> 1 | H8: =IF(H5>=Assumptions!$C$32,1,0) -> 1 | I8: =IF(I5>=Assumptions!$C$32,1,0) -> 1 | J8: =IF(J5>=Assumptions!$C$32,1,0) -> 1 | ... N8: =IF(N5>=Assumptions!$C$32,1,0) -> 1
B9: Practice 2 | C9: =IF(C5>=Assumptions!$C$33,1,0) -> 0 | D9: =IF(D5>=Assumptions!$C$33,1,0) -> 0 | E9: =IF(E5>=Assumptions!$C$33,1,0) -> 1 | F9: =IF(F5>=Assumptions!$C$33,1,0) -> 1 | G9: =IF(G5>=Assumptions!$C$33,1,0) -> 1 | H9: =IF(H5>=Assumptions!$C$33,1,0) -> 1 | I9: =IF(I5>=Assumptions!$C$33,1,0) -> 1 | J9: =IF(J5>=Assumptions!$C$33,1,0) -> 1 | ... N9: =IF(N5>=Assumptions!$C$33,1,0) -> 1
B10: Practice 3 | C10: =IF(C5>=Assumptions!$C$34,1,0) -> 0 | D10: =IF(D5>=Assumptions!$C$34,1,0) -> 0 | E10: =IF(E5>=Assumptions!$C$34,1,0) -> 0 | F10: =IF(F5>=Assumptions!$C$34,1,0) -> 0 | G10: =IF(G5>=Assumptions!$C$34,1,0) -> 1 | H10: =IF(H5>=Assumptions!$C$34,1,0) -> 1 | I10: =IF(I5>=Assumptions!$C$34,1,0) -> 1 | J10: =IF(J5>=Assumptions!$C$34,1,0) -> 1 | ... N10: =IF(N5>=Assumptions!$C$34,1,0) -> 1
B11: Practice 4 | C11: =IF(C5>=Assumptions!$C$35,1,0) -> 0 | D11: =IF(D5>=Assumptions!$C$35,1,0) -> 0 | E11: =IF(E5>=Assumptions!$C$35,1,0) -> 0 | F11: =IF(F5>=Assumptions!$C$35,1,0) -> 0 | G11: =IF(G5>=Assumptions!$C$35,1,0) -> 0 | H11: =IF(H5>=Assumptions!$C$35,1,0) -> 0 | I11: =IF(I5>=Assumptions!$C$35,1,0) -> 1 | J11: =IF(J5>=Assumptions!$C$35,1,0) -> 1 | ... N11: =IF(N5>=Assumptions!$C$35,1,0) -> 1
B12: Total active practices | C12: =SUM(C8:C11) -> 1 | D12: =SUM(D8:D11) -> 1 | E12: =SUM(E8:E11) -> 2 | F12: =SUM(F8:F11) -> 2 | G12: =SUM(G8:G11) -> 3 | H12: =SUM(H8:H11) -> 3 | I12: =SUM(I8:I11) -> 4 | J12: =SUM(J8:J11) -> 4 | ... N12: =SUM(N8:N11) -> 4
A14: Revenue per Practice (Ramp-adjusted, Monthly)
B15: Practice 1 revenue | C15: =IF(C5>=Assumptions!$C$32,1,0)*(Assumptions!$C$5 + (Assumptions!$C$10*Assumptions!$C$11*(IF((C5-Assumptions!$C$32+1)<=0,0,IF((C5-Assumptions!$C$32+1)=1,Assumptions!$C$12,IF((C5-Assumptions!$C$32+1)=2,Assumptions!$C$13,Assumptions!$C$14)))))*Assumptions!$C$6) -> 500.6 | D15: =IF(D5>=Assumptions!$C$32,1,0)*(Assumptions!$C$5 + (Assumptions!$C$10*Assumptions!$C$11*(IF((D5-Assumptions!$C$32+1)<=0,0,IF((D5-Assumptions!$C$32+1)=1,Assumptions!$C$12,IF((D5-Assumptions!$C$32+1)=2,Assumptions!$C$13,Assumptions!$C$14)))))*Assumptions!$C$6) -> 735.8 | E15: =IF(E5>=Assumptions!$C$32,1,0)*(Assumptions!$C$5 + (Assumptions!$C$10*Assumptions!$C$11*(IF((E5-Assumptions!$C$32+1)<=0,0,IF((E5-Assumptions!$C$32+1)=1,Assumptions!$C$12,IF((E5-Assumptions!$C$32+1)=2,Assumptions!$C$13,Assumptions!$C$14)))))*Assumptions!$C$6) -> 971 | F15: =IF(F5>=Assumptions!$C$32,1,0)*(Assumptions!$C$5 + (Assumptions!$C$10*Assumptions!$C$11*(IF((F5-Assumptions!$C$32+1)<=0,0,IF((F5-Assumptions!$C$32+1)=1,Assumptions!$C$12,IF((F5-Assumptions!$C$32+1)=2,Assumptions!$C$13,Assumptions!$C$14)))))*Assumptions!$C$6) -> 971 | G15: =IF(G5>=Assumptions!$C$32,1,0)*(Assumptions!$C$5 + (Assumptions!$C$10*Assumptions!$C$11*(IF((G5-Assumptions!$C$32+1)<=0,0,IF((G5-Assumptions!$C$32+1)=1,Assumptions!$C$12,IF((G5-Assumptions!$C$32+1)=2,Assumptions!$C$13,Assumptions!$C$14)))))*Assumptions!$C$6) -> 971 | H15: =IF(H5>=Assumptions!$C$32,1,0)*(Assumptions!$C$5 + (Assumptions!$C$10*Assumptions!$C$11*(IF((H5-Assumptions!$C$32+1)<=0,0,IF((H5-Assumptions!$C$32+1)=1,Assumptions!$C$12,IF((H5-Assumptions!$C$32+1)=2,Assumptions!$C$13,Assumptions!$C$14)))))*Assumptions!$C$6) -> 971 | I15: =IF(I5>=Assumptions!$C$32,1,0)*(Assumptions!$C$5 + (Assumptions!$C$10*Assumptions!$C$11*(IF((I5-Assumptions!$C$32+1)<=0,0,IF((I5-Assumptions!$C$32+1)=1,Assumptions!$C$12,IF((I5-Assumptions!$C$32+1)=2,Assumptions!$C$13,Assumptions!$C$14)))))*Assumptions!$C$6) -> 971 | J15: =IF(J5>=Assumptions!$C$32,1,0)*(Assumptions!$C$5 + (Assumptions!$C$10*Assumptions!$C$11*(IF((J5-Assumptions!$C$32+1)<=0,0,IF((J5-Assumptions!$C$32+1)=1,Assumptions!$C$12,IF((J5-Assumptions!$C$32+1)=2,Assumptions!$C$13,Assumptions!$C$14)))))*Assumptions!$C$6) -> 971 | ... N15: =IF(N5>=Assumptions!$C$32,1,0)*(Assumptions!$C$5 + (Assumptions!$C$10*Assumptions!$C$11*(IF((N5-Assumptions!$C$32+1)<=0,0,IF((N5-Assumptions!$C$32+1)=1,Assumptions!$C$12,IF((N5-Assumptions!$C$32+1)=2,Assumptions!$C$13,Assumptions!$C$14)))))*Assumptions!$C$6) -> 971
B16: Practice 2 revenue | C16: =IF(C5>=Assumptions!$C$33,1,0)*(Assumptions!$C$5 + (Assumptions!$C$10*Assumptions!$C$11*(IF((C5-Assumptions!$C$33+1)<=0,0,IF((C5-Assumptions!$C$33+1)=1,Assumptions!$C$12,IF((C5-Assumptions!$C$33+1)=2,Assumptions!$C$13,Assumptions!$C$14)))))*Assumptions!$C$6) -> 0 | D16: =IF(D5>=Assumptions!$C$33,1,0)*(Assumptions!$C$5 + (Assumptions!$C$10*Assumptions!$C$11*(IF((D5-Assumptions!$C$33+1)<=0,0,IF((D5-Assumptions!$C$33+1)=1,Assumptions!$C$12,IF((D5-Assumptions!$C$33+1)=2,Assumptions!$C$13,Assumptions!$C$14)))))*Assumptions!$C$6) -> 0 | E16: =IF(E5>=Assumptions!$C$33,1,0)*(Assumptions!$C$5 + (Assumptions!$C$10*Assumptions!$C$11*(IF((E5-Assumptions!$C$33+1)<=0,0,IF((E5-Assumptions!$C$33+1)=1,Assumptions!$C$12,IF((E5-Assumptions!$C$33+1)=2,Assumptions!$C$13,Assumptions!$C$14)))))*Assumptions!$C$6) -> 500.6 | F16: =IF(F5>=Assumptions!$C$33,1,0)*(Assumptions!$C$5 + (Assumptions!$C$10*Assumptions!$C$11*(IF((F5-Assumptions!$C$33+1)<=0,0,IF((F5-Assumptions!$C$33+1)=1,Assumptions!$C$12,IF((F5-Assumptions!$C$33+1)=2,Assumptions!$C$13,Assumptions!$C$14)))))*Assumptions!$C$6) -> 735.8 | G16: =IF(G5>=Assumptions!$C$33,1,0)*(Assumptions!$C$5 + (Assumptions!$C$10*Assumptions!$C$11*(IF((G5-Assumptions!$C$33+1)<=0,0,IF((G5-Assumptions!$C$33+1)=1,Assumptions!$C$12,IF((G5-Assumptions!$C$33+1)=2,Assumptions!$C$13,Assumptions!$C$14)))))*Assumptions!$C$6) -> 971 | H16: =IF(H5>=Assumptions!$C$33,1,0)*(Assumptions!$C$5 + (Assumptions!$C$10*Assumptions!$C$11*(IF((H5-Assumptions!$C$33+1)<=0,0,IF((H5-Assumptions!$C$33+1)=1,Assumptions!$C$12,IF((H5-Assumptions!$C$33+1)=2,Assumptions!$C$13,Assumptions!$C$14)))))*Assumptions!$C$6) -> 971 | I16: =IF(I5>=Assumptions!$C$33,1,0)*(Assumptions!$C$5 + (Assumptions!$C$10*Assumptions!$C$11*(IF((I5-Assumptions!$C$33+1)<=0,0,IF((I5-Assumptions!$C$33+1)=1,Assumptions!$C$12,IF((I5-Assumptions!$C$33+1)=2,Assumptions!$C$13,Assumptions!$C$14)))))*Assumptions!$C$6) -> 971 | J16: =IF(J5>=Assumptions!$C$33,1,0)*(Assumptions!$C$5 + (Assumptions!$C$10*Assumptions!$C$11*(IF((J5-Assumptions!$C$33+1)<=0,0,IF((J5-Assumptions!$C$33+1)=1,Assumptions!$C$12,IF((J5-Assumptions!$C$33+1)=2,Assumptions!$C$13,Assumptions!$C$14)))))*Assumptions!$C$6) -> 971 | ... N16: =IF(N5>=Assumptions!$C$33,1,0)*(Assumptions!$C$5 + (Assumptions!$C$10*Assumptions!$C$11*(IF((N5-Assumptions!$C$33+1)<=0,0,IF((N5-Assumptions!$C$33+1)=1,Assumptions!$C$12,IF((N5-Assumptions!$C$33+1)=2,Assumptions!$C$13,Assumptions!$C$14)))))*Assumptions!$C$6) -> 971
B17: Practice 3 revenue | C17: =IF(C5>=Assumptions!$C$34,1,0)*(Assumptions!$C$5 + (Assumptions!$C$10*Assumptions!$C$11*(IF((C5-Assumptions!$C$34+1)<=0,0,IF((C5-Assumptions!$C$34+1)=1,Assumptions!$C$12,IF((C5-Assumptions!$C$34+1)=2,Assumptions!$C$13,Assumptions!$C$14)))))*Assumptions!$C$6) -> 0 | D17: =IF(D5>=Assumptions!$C$34,1,0)*(Assumptions!$C$5 + (Assumptions!$C$10*Assumptions!$C$11*(IF((D5-Assumptions!$C$34+1)<=0,0,IF((D5-Assumptions!$C$34+1)=1,Assumptions!$C$12,IF((D5-Assumptions!$C$34+1)=2,Assumptions!$C$13,Assumptions!$C$14)))))*Assumptions!$C$6) -> 0 | E17: =IF(E5>=Assumptions!$C$34,1,0)*(Assumptions!$C$5 + (Assumptions!$C$10*Assumptions!$C$11*(IF((E5-Assumptions!$C$34+1)<=0,0,IF((E5-Assumptions!$C$34+1)=1,Assumptions!$C$12,IF((E5-Assumptions!$C$34+1)=2,Assumptions!$C$13,Assumptions!$C$14)))))*Assumptions!$C$6) -> 0 | F17: =IF(F5>=Assumptions!$C$34,1,0)*(Assumptions!$C$5 + (Assumptions!$C$10*Assumptions!$C$11*(IF((F5-Assumptions!$C$34+1)<=0,0,IF((F5-Assumptions!$C$34+1)=1,Assumptions!$C$12,IF((F5-Assumptions!$C$34+1)=2,Assumptions!$C$13,Assumptions!$C$14)))))*Assumptions!$C$6) -> 0 | G17: =IF(G5>=Assumptions!$C$34,1,0)*(Assumptions!$C$5 + (Assumptions!$C$10*Assumptions!$C$11*(IF((G5-Assumptions!$C$34+1)<=0,0,IF((G5-Assumptions!$C$34+1)=1,Assumptions!$C$12,IF((G5-Assumptions!$C$34+1)=2,Assumptions!$C$13,Assumptions!$C$14)))))*Assumptions!$C$6) -> 500.6 | H17: =IF(H5>=Assumptions!$C$34,1,0)*(Assumptions!$C$5 + (Assumptions!$C$10*Assumptions!$C$11*(IF((H5-Assumptions!$C$34+1)<=0,0,IF((H5-Assumptions!$C$34+1)=1,Assumptions!$C$12,IF((H5-Assumptions!$C$34+1)=2,Assumptions!$C$13,Assumptions!$C$14)))))*Assumptions!$C$6) -> 735.8 | I17: =IF(I5>=Assumptions!$C$34,1,0)*(Assumptions!$C$5 + (Assumptions!$C$10*Assumptions!$C$11*(IF((I5-Assumptions!$C$34+1)<=0,0,IF((I5-Assumptions!$C$34+1)=1,Assumptions!$C$12,IF((I5-Assumptions!$C$34+1)=2,Assumptions!$C$13,Assumptions!$C$14)))))*Assumptions!$C$6) -> 971 | J17: =IF(J5>=Assumptions!$C$34,1,0)*(Assumptions!$C$5 + (Assumptions!$C$10*Assumptions!$C$11*(IF((J5-Assumptions!$C$34+1)<=0,0,IF((J5-Assumptions!$C$34+1)=1,Assumptions!$C$12,IF((J5-Assumptions!$C$34+1)=2,Assumptions!$C$13,Assumptions!$C$14)))))*Assumptions!$C$6) -> 971 | ... N17: =IF(N5>=Assumptions!$C$34,1,0)*(Assumptions!$C$5 + (Assumptions!$C$10*Assumptions!$C$11*(IF((N5-Assumptions!$C$34+1)<=0,0,IF((N5-Assumptions!$C$34+1)=1,Assumptions!$C$12,IF((N5-Assumptions!$C$34+1)=2,Assumptions!$C$13,Assumptions!$C$14)))))*Assumptions!$C$6) -> 971
B18: Practice 4 revenue | C18: =IF(C5>=Assumptions!$C$35,1,0)*(Assumptions!$C$5 + (Assumptions!$C$10*Assumptions!$C$11*(IF((C5-Assumptions!$C$35+1)<=0,0,IF((C5-Assumptions!$C$35+1)=1,Assumptions!$C$12,IF((C5-Assumptions!$C$35+1)=2,Assumptions!$C$13,Assumptions!$C$14)))))*Assumptions!$C$6) -> 0 | D18: =IF(D5>=Assumptions!$C$35,1,0)*(Assumptions!$C$5 + (Assumptions!$C$10*Assumptions!$C$11*(IF((D5-Assumptions!$C$35+1)<=0,0,IF((D5-Assumptions!$C$35+1)=1,Assumptions!$C$12,IF((D5-Assumptions!$C$35+1)=2,Assumptions!$C$13,Assumptions!$C$14)))))*Assumptions!$C$6) -> 0 | E18: =IF(E5>=Assumptions!$C$35,1,0)*(Assumptions!$C$5 + (Assumptions!$C$10*Assumptions!$C$11*(IF((E5-Assumptions!$C$35+1)<=0,0,IF((E5-Assumptions!$C$35+1)=1,Assumptions!$C$12,IF((E5-Assumptions!$C$35+1)=2,Assumptions!$C$13,Assumptions!$C$14)))))*Assumptions!$C$6) -> 0 | F18: =IF(F5>=Assumptions!$C$35,1,0)*(Assumptions!$C$5 + (Assumptions!$C$10*Assumptions!$C$11*(IF((F5-Assumptions!$C$35+1)<=0,0,IF((F5-Assumptions!$C$35+1)=1,Assumptions!$C$12,IF((F5-Assumptions!$C$35+1)=2,Assumptions!$C$13,Assumptions!$C$14)))))*Assumptions!$C$6) -> 0 | G18: =IF(G5>=Assumptions!$C$35,1,0)*(Assumptions!$C$5 + (Assumptions!$C$10*Assumptions!$C$11*(IF((G5-Assumptions!$C$35+1)<=0,0,IF((G5-Assumptions!$C$35+1)=1,Assumptions!$C$12,IF((G5-Assumptions!$C$35+1)=2,Assumptions!$C$13,Assumptions!$C$14)))))*Assumptions!$C$6) -> 0 | H18: =IF(H5>=Assumptions!$C$35,1,0)*(Assumptions!$C$5 + (Assumptions!$C$10*Assumptions!$C$11*(IF((H5-Assumptions!$C$35+1)<=0,0,IF((H5-Assumptions!$C$35+1)=1,Assumptions!$C$12,IF((H5-Assumptions!$C$35+1)=2,Assumptions!$C$13,Assumptions!$C$14)))))*Assumptions!$C$6) -> 0 | I18: =IF(I5>=Assumptions!$C$35,1,0)*(Assumptions!$C$5 + (Assumptions!$C$10*Assumptions!$C$11*(IF((I5-Assumptions!$C$35+1)<=0,0,IF((I5-Assumptions!$C$35+1)=1,Assumptions!$C$12,IF((I5-Assumptions!$C$35+1)=2,Assumptions!$C$13,Assumptions!$C$14)))))*Assumptions!$C$6) -> 500.6 | J18: =IF(J5>=Assumptions!$C$35,1,0)*(Assumptions!$C$5 + (Assumptions!$C$10*Assumptions!$C$11*(IF((J5-Assumptions!$C$35+1)<=0,0,IF((J5-Assumptions!$C$35+1)=1,Assumptions!$C$12,IF((J5-Assumptions!$C$35+1)=2,Assumptions!$C$13,Assumptions!$C$14)))))*Assumptions!$C$6) -> 735.8 | ... N18: =IF(N5>=Assumptions!$C$35,1,0)*(Assumptions!$C$5 + (Assumptions!$C$10*Assumptions!$C$11*(IF((N5-Assumptions!$C$35+1)<=0,0,IF((N5-Assumptions!$C$35+1)=1,Assumptions!$C$12,IF((N5-Assumptions!$C$35+1)=2,Assumptions!$C$13,Assumptions!$C$14)))))*Assumptions!$C$6) -> 971
B19: Total monthly revenue | C19: =SUM(C15:C18) -> 500.6 | D19: =SUM(D15:D18) -> 735.8 | E19: =SUM(E15:E18) -> 1471.6 | F19: =SUM(F15:F18) -> 1706.8 | G19: =SUM(G15:G18) -> 2442.6 | H19: =SUM(H15:H18) -> 2677.8 | I19: =SUM(I15:I18) -> 3413.6 | J19: =SUM(J15:J18) -> 3648.8 | ... N19: =SUM(N15:N18) -> 3884 | O19: =SUM(C19:N19) -> 32133.6
A21: Costs (Monthly)
B22: Variable costs (per-practice × active) | C22: =(Assumptions!$C$17+Assumptions!$C$18+Assumptions!$C$20)*C12+Assumptions!$C$19*C19 -> 419.5174 | D22: =(Assumptions!$C$17+Assumptions!$C$18+Assumptions!$C$20)*D12+Assumptions!$C$19*D19 -> 426.3382 | E22: =(Assumptions!$C$17+Assumptions!$C$18+Assumptions!$C$20)*E12+Assumptions!$C$19*E19 -> 852.6764 | F22: =(Assumptions!$C$17+Assumptions!$C$18+Assumptions!$C$20)*F12+Assumptions!$C$19*F19 -> 859.4972 | G22: =(Assumptions!$C$17+Assumptions!$C$18+Assumptions!$C$20)*G12+Assumptions!$C$19*G19 -> 1285.8354 | H22: =(Assumptions!$C$17+Assumptions!$C$18+Assumptions!$C$20)*H12+Assumptions!$C$19*H19 -> 1292.6562 | I22: =(Assumptions!$C$17+Assumptions!$C$18+Assumptions!$C$20)*I12+Assumptions!$C$19*I19 -> 1718.9944 | J22: =(Assumptions!$C$17+Assumptions!$C$18+Assumptions!$C$20)*J12+Assumptions!$C$19*J19 -> 1725.8152 | ... N22: =(Assumptions!$C$17+Assumptions!$C$18+Assumptions!$C$20)*N12+Assumptions!$C$19*N19 -> 1732.636 | O22: =SUM(C22:N22) -> 15511.874
B23: Fixed costs (company-wide) | C23: =Assumptions!$C$29 -> 950 | D23: =Assumptions!$C$29 -> 950 | E23: =Assumptions!$C$29 -> 950 | F23: =Assumptions!$C$29 -> 950 | G23: =Assumptions!$C$29 -> 950 | H23: =Assumptions!$C$29 -> 950 | I23: =Assumptions!$C$29 -> 950 | J23: =Assumptions!$C$29 -> 950 | ... N23: =Assumptions!$C$29 -> 950 | O23: =SUM(C23:N23) -> 11400
B24: Total monthly costs | C24: =C22+C23 -> 1369.5174 | D24: =D22+D23 -> 1376.3382 | E24: =E22+E23 -> 1802.6764 | F24: =F22+F23 -> 1809.4972 | G24: =G22+G23 -> 2235.8354 | H24: =H22+H23 -> 2242.6562 | I24: =I22+I23 -> 2668.9944 | J24: =J22+J23 -> 2675.8152 | ... N24: =N22+N23 -> 2682.636 | O24: =SUM(C24:N24) -> 26911.874
A26: Cash Flow
B27: Net income (pre-tax) | C27: =C19-C24 -> -868.9174 | D27: =D19-D24 -> -640.5382 | E27: =E19-E24 -> -331.0764 | F27: =F19-F24 -> -102.6972 | G27: =G19-G24 -> 206.7646 | H27: =H19-H24 -> 435.1438 | I27: =I19-I24 -> 744.6056 | J27: =J19-J24 -> 972.9848 | ... N27: =N19-N24 -> 1201.364 | O27: =SUM(C27:N27) -> 5221.7256
B28: Cumulative cash position | C28: =C27 -> -868.9174 | D28: =C28+D27 -> -1509.4556 | E28: =D28+E27 -> -1840.532 | F28: =E28+F27 -> -1943.2292 | G28: =F28+G27 -> -1736.4646 | H28: =G28+H27 -> -1301.3208 | I28: =H28+I27 -> -556.7152 | J28: =I28+J27 -> 416.2696 | K28: =J28+K27 -> 1617.6336 | ... N28: =M28+N27 -> 5221.7256 | O28: =N28 -> 5221.7256
A31: Year 1 Summary
B32: Year 1 total revenue | C32: =O19 -> 32133.6
B33: Year 1 total costs | C33: =O24 -> 26911.874
B34: Year 1 net income | C34: =O27 -> 5221.7256
B35: Year 1 gross margin % | C35: =IFERROR((O19-O22)/O19,0) -> 0.51726933
B36: Exit run-rate MRR (Month 12) | C36: =N19 -> 3884
B37: Exit run-rate ARR (annualized) | C37: =N19*12 -> 46608

Sheet Pricing Scenarios
A1: Pricing Scenarios — Sensitivity Analysis
A2: Monthly revenue per practice in steady state. Columns = Success fee %. Rows = Monthly base fee.
A4: Monthly Revenue per Practice (Steady State)
B5: Base fee ↓ / Success % → | C5: 0.08 | D5: 0.1 | E5: 0.12 | F5: 0.15 | G5: 0.18 | H5: 0.2
B6: 0 | C6: =0+(Assumptions!$C$10*Assumptions!$C$11)*0.08 -> 448 | D6: =0+(Assumptions!$C$10*Assumptions!$C$11)*0.1 -> 560 | E6: =0+(Assumptions!$C$10*Assumptions!$C$11)*0.12 -> 672 | F6: =0+(Assumptions!$C$10*Assumptions!$C$11)*0.15 -> 840 | G6: =0+(Assumptions!$C$10*Assumptions!$C$11)*0.18 -> 1008 | H6: =0+(Assumptions!$C$10*Assumptions!$C$11)*0.2 -> 1120
B7: 199 | C7: =199+(Assumptions!$C$10*Assumptions!$C$11)*0.08 -> 647 | D7: =199+(Assumptions!$C$10*Assumptions!$C$11)*0.1 -> 759 | E7: =199+(Assumptions!$C$10*Assumptions!$C$11)*0.12 -> 871 | F7: =199+(Assumptions!$C$10*Assumptions!$C$11)*0.15 -> 1039 | G7: =199+(Assumptions!$C$10*Assumptions!$C$11)*0.18 -> 1207 | H7: =199+(Assumptions!$C$10*Assumptions!$C$11)*0.2 -> 1319
B8: 299 | C8: =299+(Assumptions!$C$10*Assumptions!$C$11)*0.08 -> 747 | D8: =299+(Assumptions!$C$10*Assumptions!$C$11)*0.1 -> 859 | E8: =299+(Assumptions!$C$10*Assumptions!$C$11)*0.12 -> 971 | F8: =299+(Assumptions!$C$10*Assumptions!$C$11)*0.15 -> 1139 | G8: =299+(Assumptions!$C$10*Assumptions!$C$11)*0.18 -> 1307 | H8: =299+(Assumptions!$C$10*Assumptions!$C$11)*0.2 -> 1419
B9: 399 | C9: =399+(Assumptions!$C$10*Assumptions!$C$11)*0.08 -> 847 | D9: =399+(Assumptions!$C$10*Assumptions!$C$11)*0.1 -> 959 | E9: =399+(Assumptions!$C$10*Assumptions!$C$11)*0.12 -> 1071 | F9: =399+(Assumptions!$C$10*Assumptions!$C$11)*0.15 -> 1239 | G9: =399+(Assumptions!$C$10*Assumptions!$C$11)*0.18 -> 1407 | H9: =399+(Assumptions!$C$10*Assumptions!$C$11)*0.2 -> 1519
B10: 499 | C10: =499+(Assumptions!$C$10*Assumptions!$C$11)*0.08 -> 947 | D10: =499+(Assumptions!$C$10*Assumptions!$C$11)*0.1 -> 1059 | E10: =499+(Assumptions!$C$10*Assumptions!$C$11)*0.12 -> 1171 | F10: =499+(Assumptions!$C$10*Assumptions!$C$11)*0.15 -> 1339 | G10: =499+(Assumptions!$C$10*Assumptions!$C$11)*0.18 -> 1507 | H10: =499+(Assumptions!$C$10*Assumptions!$C$11)*0.2 -> 1619
B11: 599 | C11: =599+(Assumptions!$C$10*Assumptions!$C$11)*0.08 -> 1047 | D11: =599+(Assumptions!$C$10*Assumptions!$C$11)*0.1 -> 1159 | E11: =599+(Assumptions!$C$10*Assumptions!$C$11)*0.12 -> 1271 | F11: =599+(Assumptions!$C$10*Assumptions!$C$11)*0.15 -> 1439 | G11: =599+(Assumptions!$C$10*Assumptions!$C$11)*0.18 -> 1607 | H11: =599+(Assumptions!$C$10*Assumptions!$C$11)*0.2 -> 1719
A14: Practices Needed to Break Even (cover fixed costs)
B15: Base fee ↓ / Success % → | C15: 0.08 | D15: 0.1 | E15: 0.12 | F15: 0.15 | G15: 0.18 | H15: 0.2
B16: 0 | C16: =IFERROR(CEILING(Assumptions!$C$29/((0+(Assumptions!$C$10*Assumptions!$C$11)*0.08)*(1-Assumptions!$C$19)-Assumptions!$C$17-Assumptions!$C$18-Assumptions!$C$20),1),"n/a") -> 32 | D16: =IFERROR(CEILING(Assumptions!$C$29/((0+(Assumptions!$C$10*Assumptions!$C$11)*0.1)*(1-Assumptions!$C$19)-Assumptions!$C$17-Assumptions!$C$18-Assumptions!$C$20),1),"n/a") -> 7 | E16: =IFERROR(CEILING(Assumptions!$C$29/((0+(Assumptions!$C$10*Assumptions!$C$11)*0.12)*(1-Assumptions!$C$19)-Assumptions!$C$17-Assumptions!$C$18-Assumptions!$C$20),1),"n/a") -> 4 | F16: =IFERROR(CEILING(Assumptions!$C$29/((0+(Assumptions!$C$10*Assumptions!$C$11)*0.15)*(1-Assumptions!$C$19)-Assumptions!$C$17-Assumptions!$C$18-Assumptions!$C$20),1),"n/a") -> 3 | G16: =IFERROR(CEILING(Assumptions!$C$29/((0+(Assumptions!$C$10*Assumptions!$C$11)*0.18)*(1-Assumptions!$C$19)-Assumptions!$C$17-Assumptions!$C$18-Assumptions!$C$20),1),"n/a") -> 2 | H16: =IFERROR(CEILING(Assumptions!$C$29/((0+(Assumptions!$C$10*Assumptions!$C$11)*0.2)*(1-Assumptions!$C$19)-Assumptions!$C$17-Assumptions!$C$18-Assumptions!$C$20),1),"n/a") -> 2
B17: 199 | C17: =IFERROR(CEILING(Assumptions!$C$29/((199+(Assumptions!$C$10*Assumptions!$C$11)*0.08)*(1-Assumptions!$C$19)-Assumptions!$C$17-Assumptions!$C$18-Assumptions!$C$20),1),"n/a") -> 5 | D17: =IFERROR(CEILING(Assumptions!$C$29/((199+(Assumptions!$C$10*Assumptions!$C$11)*0.1)*(1-Assumptions!$C$19)-Assumptions!$C$17-Assumptions!$C$18-Assumptions!$C$20),1),"n/a") -> 3 | E17: =IFERROR(CEILING(Assumptions!$C$29/((199+(Assumptions!$C$10*Assumptions!$C$11)*0.12)*(1-Assumptions!$C$19)-Assumptions!$C$17-Assumptions!$C$18-Assumptions!$C$20),1),"n/a") -> 3 | F17: =IFERROR(CEILING(Assumptions!$C$29/((199+(Assumptions!$C$10*Assumptions!$C$11)*0.15)*(1-Assumptions!$C$19)-Assumptions!$C$17-Assumptions!$C$18-Assumptions!$C$20),1),"n/a") -> 2 | G17: =IFERROR(CEILING(Assumptions!$C$29/((199+(Assumptions!$C$10*Assumptions!$C$11)*0.18)*(1-Assumptions!$C$19)-Assumptions!$C$17-Assumptions!$C$18-Assumptions!$C$20),1),"n/a") -> 2 | H17: =IFERROR(CEILING(Assumptions!$C$29/((199+(Assumptions!$C$10*Assumptions!$C$11)*0.2)*(1-Assumptions!$C$19)-Assumptions!$C$17-Assumptions!$C$18-Assumptions!$C$20),1),"n/a") -> 2
B18: 299 | C18: =IFERROR(CEILING(Assumptions!$C$29/((299+(Assumptions!$C$10*Assumptions!$C$11)*0.08)*(1-Assumptions!$C$19)-Assumptions!$C$17-Assumptions!$C$18-Assumptions!$C$20),1),"n/a") -> 3 | D18: =IFERROR(CEILING(Assumptions!$C$29/((299+(Assumptions!$C$10*Assumptions!$C$11)*0.1)*(1-Assumptions!$C$19)-Assumptions!$C$17-Assumptions!$C$18-Assumptions!$C$20),1),"n/a") -> 3 | E18: =IFERROR(CEILING(Assumptions!$C$29/((299+(Assumptions!$C$10*Assumptions!$C$11)*0.12)*(1-Assumptions!$C$19)-Assumptions!$C$17-Assumptions!$C$18-Assumptions!$C$20),1),"n/a") -> 2 | F18: =IFERROR(CEILING(Assumptions!$C$29/((299+(Assumptions!$C$10*Assumptions!$C$11)*0.15)*(1-Assumptions!$C$19)-Assumptions!$C$17-Assumptions!$C$18-Assumptions!$C$20),1),"n/a") -> 2 | G18: =IFERROR(CEILING(Assumptions!$C$29/((299+(Assumptions!$C$10*Assumptions!$C$11)*0.18)*(1-Assumptions!$C$19)-Assumptions!$C$17-Assumptions!$C$18-Assumptions!$C$20),1),"n/a") -> 2 | H18: =IFERROR(CEILING(Assumptions!$C$29/((299+(Assumptions!$C$10*Assumptions!$C$11)*0.2)*(1-Assumptions!$C$19)-Assumptions!$C$17-Assumptions!$C$18-Assumptions!$C$20),1),"n/a") -> 1
B19: 399 | C19: =IFERROR(CEILING(Assumptions!$C$29/((399+(Assumptions!$C$10*Assumptions!$C$11)*0.08)*(1-Assumptions!$C$19)-Assumptions!$C$17-Assumptions!$C$18-Assumptions!$C$20),1),"n/a") -> 3 | D19: =IFERROR(CEILING(Assumptions!$C$29/((399+(Assumptions!$C$10*Assumptions!$C$11)*0.1)*(1-Assumptions!$C$19)-Assumptions!$C$17-Assumptions!$C$18-Assumptions!$C$20),1),"n/a") -> 2 | E19: =IFERROR(CEILING(Assumptions!$C$29/((399+(Assumptions!$C$10*Assumptions!$C$11)*0.12)*(1-Assumptions!$C$19)-Assumptions!$C$17-Assumptions!$C$18-Assumptions!$C$20),1),"n/a") -> 2 | F19: =IFERROR(CEILING(Assumptions!$C$29/((399+(Assumptions!$C$10*Assumptions!$C$11)*0.15)*(1-Assumptions!$C$19)-Assumptions!$C$17-Assumptions!$C$18-Assumptions!$C$20),1),"n/a") -> 2 | G19: =IFERROR(CEILING(Assumptions!$C$29/((399+(Assumptions!$C$10*Assumptions!$C$11)*0.18)*(1-Assumptions!$C$19)-Assumptions!$C$17-Assumptions!$C$18-Assumptions!$C$20),1),"n/a") -> 1 | H19: =IFERROR(CEILING(Assumptions!$C$29/((399+(Assumptions!$C$10*Assumptions!$C$11)*0.2)*(1-Assumptions!$C$19)-Assumptions!$C$17-Assumptions!$C$18-Assumptions!$C$20),1),"n/a") -> 1
B20: 499 | C20: =IFERROR(CEILING(Assumptions!$C$29/((499+(Assumptions!$C$10*Assumptions!$C$11)*0.08)*(1-Assumptions!$C$19)-Assumptions!$C$17-Assumptions!$C$18-Assumptions!$C$20),1),"n/a") -> 2 | D20: =IFERROR(CEILING(Assumptions!$C$29/((499+(Assumptions!$C$10*Assumptions!$C$11)*0.1)*(1-Assumptions!$C$19)-Assumptions!$C$17-Assumptions!$C$18-Assumptions!$C$20),1),"n/a") -> 2 | E20: =IFERROR(CEILING(Assumptions!$C$29/((499+(Assumptions!$C$10*Assumptions!$C$11)*0.12)*(1-Assumptions!$C$19)-Assumptions!$C$17-Assumptions!$C$18-Assumptions!$C$20),1),"n/a") -> 2 | F20: =IFERROR(CEILING(Assumptions!$C$29/((499+(Assumptions!$C$10*Assumptions!$C$11)*0.15)*(1-Assumptions!$C$19)-Assumptions!$C$17-Assumptions!$C$18-Assumptions!$C$20),1),"n/a") -> 2 | G20: =IFERROR(CEILING(Assumptions!$C$29/((499+(Assumptions!$C$10*Assumptions!$C$11)*0.18)*(1-Assumptions!$C$19)-Assumptions!$C$17-Assumptions!$C$18-Assumptions!$C$20),1),"n/a") -> 1 | H20: =IFERROR(CEILING(Assumptions!$C$29/((499+(Assumptions!$C$10*Assumptions!$C$11)*0.2)*(1-Assumptions!$C$19)-Assumptions!$C$17-Assumptions!$C$18-Assumptions!$C$20),1),"n/a") -> 1
B21: 599 | C21: =IFERROR(CEILING(Assumptions!$C$29/((599+(Assumptions!$C$10*Assumptions!$C$11)*0.08)*(1-Assumptions!$C$19)-Assumptions!$C$17-Assumptions!$C$18-Assumptions!$C$20),1),"n/a") -> 2 | D21: =IFERROR(CEILING(Assumptions!$C$29/((599+(Assumptions!$C$10*Assumptions!$C$11)*0.1)*(1-Assumptions!$C$19)-Assumptions!$C$17-Assumptions!$C$18-Assumptions!$C$20),1),"n/a") -> 2 | E21: =IFERROR(CEILING(Assumptions!$C$29/((599+(Assumptions!$C$10*Assumptions!$C$11)*0.12)*(1-Assumptions!$C$19)-Assumptions!$C$17-Assumptions!$C$18-Assumptions!$C$20),1),"n/a") -> 2 | F21: =IFERROR(CEILING(Assumptions!$C$29/((599+(Assumptions!$C$10*Assumptions!$C$11)*0.15)*(1-Assumptions!$C$19)-Assumptions!$C$17-Assumptions!$C$18-Assumptions!$C$20),1),"n/a") -> 1 | G21: =IFERROR(CEILING(Assumptions!$C$29/((599+(Assumptions!$C$10*Assumptions!$C$11)*0.18)*(1-Assumptions!$C$19)-Assumptions!$C$17-Assumptions!$C$18-Assumptions!$C$20),1),"n/a") -> 1 | H21: =IFERROR(CEILING(Assumptions!$C$29/((599+(Assumptions!$C$10*Assumptions!$C$11)*0.2)*(1-Assumptions!$C$19)-Assumptions!$C$17-Assumptions!$C$18-Assumptions!$C$20),1),"n/a") -> 1
B24: Recommendation:
B25: Current pilot pricing (base $299, success 12%) is highlighted yellow. It's defensibly priced against Canadian RCM competitors
B26: while leaving headroom: contribution per practice is strong enough that 3-4 pilot practices cover fixed costs.
B27: Raise pricing after pilot when you have case-study recovery numbers from Dr. Hasan — move to $399 base / 15% success for scale.
B28: Consider offering a 3-month pilot discount: $0 base + 15% success. Converts hesitant practices; success fee protects your margin.

Sheet Sample Invoice
A1: Sample Monthly Invoice — Dr. Hasan's Practice
A2: This is what one practice receives each month. Stripe Billing can generate this automatically.
A4: Invoice Details
B5: Invoice to: | C5: Tenth Line Family Dentistry — Dr. Hasan
B6: Practice ID: | C6: CRX-001
B7: Billing period: | C7: April 1–30, 2026
B8: Invoice date: | C8: May 1, 2026
B9: Due: | C9: Net 0 (auto-debit via Stripe ACH)
A11: Line Items
B12: Description | C12: Calculation | D12: Amount (CAD)
B13: CollectRx Platform — Monthly Base | C13: =TEXT(Assumptions!$C$5, "$#,##0") & " flat" -> $299 flat | D13: =Assumptions!$C$5 -> 299
B14: Recovered AR this month (illustrative) | D14: 6000
B15: Success fee on recovered AR | C15: =TEXT(Assumptions!$C$6,"0%") & " of recovered" -> 12% of recovered | D15: =D14*Assumptions!$C$6 -> 720
B16: Subtotal | D16: =D13+D15 -> 1019
B17: HST (Ontario) | C17: =TEXT(Assumptions!$C$7,"0%") & " × subtotal" -> 13% × subtotal | D17: =D16*Assumptions!$C$7 -> 132.47
B18: TOTAL DUE | D18: =D16+D17 -> 1151.47
A20: What CollectRx Nets from This Invoice
B21: Gross invoice revenue (ex-HST) | D21: =D16 -> 1019
B22: Less: Stripe processing fees | D22: =-D16*Assumptions!$C$19 -> -29.551
B23: Less: Vapi attributable to this practice | D23: =-Assumptions!$C$17 -> -280
B24: Less: Twilio attributable to this practice | D24: =-Assumptions!$C$18 -> -75
B25: Less: Other variable cost | D25: =-Assumptions!$C$20 -> -50
B26: Net contribution to CollectRx | D26: =SUM(D21:D25) -> 584.449
B28: Note on HST: Collected from practice, held in trust, remitted to CRA quarterly. Not your revenue.
